ParaCode/RunShell.py
ParaCode/__init__.py
ParaCode/basic.py
ParaCode/config.py
ParaCode/shell.py
ParaCode/strings_with_arrows.py
ParaCode-1.2.20.4.dist-info/LICENSE
ParaCode-1.2.20.4.dist-info/METADATA
ParaCode-1.2.20.4.dist-info/WHEEL
ParaCode-1.2.20.4.dist-info/top_level.txt
ParaCode-1.2.20.4.dist-info/RECORD
